taskq/version.py
taskq/__init__.py
taskq/policy.py
taskq/queue.py
taskq-0.3.dist-info/RECORD
taskq-0.3.dist-info/DESCRIPTION.rst
taskq-0.3.dist-info/zip-safe
taskq-0.3.dist-info/top_level.txt
taskq-0.3.dist-info/METADATA
taskq-0.3.dist-info/metadata.json
taskq-0.3.dist-info/WHEEL
